LICENSE.md
README.md
pyproject.toml
fides/__init__.py
fides/constants.py
fides/hessian_approximation.py
fides/logging.py
fides/minimize.py
fides/stepback.py
fides/steps.py
fides/subproblem.py
fides/trust_region.py
fides/version.py
fides.egg-info/PKG-INFO
fides.egg-info/SOURCES.txt
fides.egg-info/dependency_links.txt
fides.egg-info/requires.txt
fides.egg-info/top_level.txt
tests/test_hessian_approximation.py
tests/test_minimize.py
tests/test_subproblem.py