Metadata-Version: 2.4
Name: fides
Version: 0.8.0
Summary: python-based Trust Region Optimization toolbox
Author-email: The fides developers <frohlichfab@gmail.com>
Maintainer-email: Fabian Fröhlich <frohlichfab@gmail.com>
License: BSD-3-Clause
Project-URL: Homepage, https://github.com/fides-dev/fides
Project-URL: Download, https://github.com/fides-dev/fides/releases
Project-URL: Bug Tracker, https://github.com/fides-dev/fides/issues
Project-URL: Documentation, https://fides-optimizer.readthedocs.io/
Project-URL: Changelog, https://github.com/fides-dev/fides/releases
Keywords: optimization,trust-region,systems biology
Classifier: Development Status :: 4 - Beta
Classifier: Topic :: Software Development :: Libraries
Classifier: Intended Audience :: Science/Research
Classifier: License :: OSI Approved :: BSD License
Classifier: Operating System :: OS Independent
Classifier: Programming Language :: Python
Classifier: Programming Language :: Python :: 3 :: Only
Classifier: Programming Language :: Python :: 3.9
Classifier: Programming Language :: Python :: 3.10
Classifier: Programming Language :: Python :: 3.11
Requires-Python: >=3.9
License-File: LICENSE.md
Requires-Dist: numpy>=1.19.2
Requires-Dist: scipy>=1.5.2
Requires-Dist: h5py>=3.5.0
Provides-Extra: test
Requires-Dist: pytest>=5.4.2; extra == "test"
Requires-Dist: pytest-cov>=4.0.0; extra == "test"
Requires-Dist: flake8>=3.7.2; extra == "test"
Dynamic: license-file
